eagles/__init__.py
eagles/config.py
eagles/Exploratory/__init__.py
eagles/Exploratory/categories.py
eagles/Exploratory/distributions.py
eagles/Exploratory/explore.py
eagles/Exploratory/missing.py
eagles/Exploratory/outcomes.py
eagles/Exploratory/utils/__init__.py
eagles/Exploratory/utils/plot_utils.py
eagles/Stats/__init__.py
eagles/Stats/archive.py
eagles/Stats/assumptions.py
eagles/Stats/chi_squared.py
eagles/Stats/compare_proportions.py
eagles/Stats/config.py
eagles/Stats/effect_size.py
eagles/Stats/plot_utils.py
eagles/Stats/power.py
eagles/Stats/utils.py
eagles/Stats/nonparametric/__init__.py
eagles/Stats/nonparametric/compare_means.py
eagles/Stats/nonparametric/regress.py
eagles/Stats/parametric/__init__.py
eagles/Stats/parametric/compare_means.py
eagles/Stats/parametric/regress.py
eagles/Supervised/__init__.py
eagles/Supervised/config.py
eagles/Supervised/model_init.py
eagles/Supervised/model_support.py
eagles/Supervised/supervised_tuner.py
eagles/Supervised/utils/__init__.py
eagles/Supervised/utils/feature_selection.py
eagles/Supervised/utils/logger_utils.py
eagles/Supervised/utils/metric_utils.py
eagles/Supervised/utils/plot_utils.py
eagles/Supervised/utils/tuner_utils.py
eagles/Unsupervised/__init__.py
eagles/Unsupervised/_graph_clustering.py
eagles/Unsupervised/unsupervised_tuner.py
eagles/Unsupervised/utils/__init__.py
eagles/Unsupervised/utils/cluster_eval_utils.py
eagles/Unsupervised/utils/logger_utils.py
eagles/Unsupervised/utils/plot_utils.py
eagles/data_sets/__init__.py
eagles/data_sets/data_loader.py
eagles/data_sets/iris.csv
eagles/data_sets/wines.csv
eagles-0.1.21.dist-info/LICENSE.txt
eagles-0.1.21.dist-info/METADATA
eagles-0.1.21.dist-info/WHEEL
eagles-0.1.21.dist-info/top_level.txt
eagles-0.1.21.dist-info/RECORD
