Metadata-Version: 2.1
Name: eagles
Version: 0.1.21
Summary: Data science utility package to help practitioners do ML and EDA work.
Home-page: https://github.com/JFLandrigan/eagles
Author: Jon-Frederick Landrigan
Author-email: jon.landrigan@gmail.com
License: UNKNOWN
Platform: UNKNOWN
Requires-Dist: ipython
Requires-Dist: kneed
Requires-Dist: matplotlib
Requires-Dist: numpy
Requires-Dist: pandas
Requires-Dist: scikit-learn
Requires-Dist: scikit-optimize
Requires-Dist: scipy
Requires-Dist: seaborn
Requires-Dist: statsmodels
